{
  "project_info": {
    "project_number": "371518812980",
    "firebase_url": "https://gkdnt-2d508-default-rtdb.firebaseio.com",
    "project_id": "gkdnt-2d508",
    "storage_bucket": "gkdnt-2d508.appspot.com"
  },
  "client": [
    {
      "client_info": {
        "mobilesdk_app_id": "1:371518812980:android:35c39f0a4d9edd2764ab61",
        "android_client_info": {
          "package_name": "com.example.gk_dnt"
        }
      },
      "oauth_client": [],
      "api_key": [
        {
          "current_key": "AIzaSyCY47ysJ5ry4WLB6jaVw59ltgDtYo0vGEg"
        }
      ],
      "services": {
        "appinvite_service": {
          "other_platform_oauth_client": []
        }
      }
    }
  ],
  "configuration_version": "1"
}